COPYING
COPYING.LESSER
INSTALL.rst
MANIFEST.in
README.rst
setup.cfg
setup.py
dbinfo/__init__.py
dbinfo/dbinfo.py
dbinfo/dbtable.py
dbinfo/dbtableref.py
dbinfo/mysql.py
dbinfo/postgres.py
dbinfo.egg-info/PKG-INFO
dbinfo.egg-info/SOURCES.txt
dbinfo.egg-info/dependency_links.txt
dbinfo.egg-info/entry_points.txt
dbinfo.egg-info/not-zip-safe
dbinfo.egg-info/requires.txt
dbinfo.egg-info/top_level.txt