Metadata-Version: 1.1
Name: dbinfo
Version: 0.1.beta2
Summary: Database Information Tool
Home-page: https://launchpad.net/dbinfo
Author: Mariano Ruiz
Author-email: mrsarm@gmail.com
License: LGPL-3
Download-URL: https://launchpad.net/dbinfo/trunk/0.1.beta2/+download/dbinfo-0.1.beta2.tar.gz
Platform: any
Classifier: Development Status :: 4 - Beta
Classifier: Environment :: Console
Classifier: Intended Audience :: Customer Service
Classifier: License :: OSI Approved :: GNU Library or Lesser General Public License (LGPL)
Classifier: Operating System :: OS Independent
Classifier: Programming Language :: Python
Classifier: Topic :: Database
